funtasks/__init__.py
funtasks/__main__.py
funtasks/tasks.py
funtasks-0.1.21.dist-info/LICENSE
funtasks-0.1.21.dist-info/METADATA
funtasks-0.1.21.dist-info/WHEEL
funtasks-0.1.21.dist-info/entry_points.txt
funtasks-0.1.21.dist-info/top_level.txt
funtasks-0.1.21.dist-info/RECORD
