Metadata-Version: 2.1
Name: funtasks
Version: 0.1.21
Summary: A task generating package that lets you add, complete, and fetch random tasks.
Author-email: Jun Li <jljune9li@gmail.com>, Natalie Ovcarov <nataliovcharov@gmail.com>, Daniel Brito <db4471@nyu.edu>, Alvaro Martinez <amm9871@nyu.edu>
License: GNU GENERAL PUBLIC LICENSE
Project-URL: Homepage, https://github.com/software-students-fall2024/3-python-package-java_and_the_scripts_
Project-URL: Repository, https://github.com/software-students-fall2024/3-python-package-java_and_the_scripts_.git
Project-URL: Bug Tracker, https://github.com/software-students-fall2024/3-python-package-java_and_the_scripts_/issues
Keywords: task generator,productivity,random tasks
Classifier: Programming Language :: Python :: 3
Classifier: Intended Audience :: Developers
Classifier: License :: OSI Approved :: GNU General Public License v3 (GPLv3)
Classifier: Operating System :: OS Independent
Requires-Python: >=3.7
License-File: LICENSE
Provides-Extra: dev
Requires-Dist: pytest; extra == "dev"
